setup.py
sogl/__init__.py
sogl/_basic.py
sogl/_bmpshape.py
sogl/_canvas.py
sogl/_composit.py
sogl/_diagram.py
sogl/_divided.py
sogl/_drawn.py
sogl/_lines.py
sogl/_soglmisc.py
sogl.egg-info/PKG-INFO
sogl.egg-info/SOURCES.txt
sogl.egg-info/dependency_links.txt
sogl.egg-info/requires.txt
sogl.egg-info/top_level.txt