Metadata-Version: 1.0
Name: sogl
Version: 0.2.1
Summary: Simplified Object Graph Library
Home-page: https://github.com/SGWissInfo/sogl
Author: Alexander Held
Author-email: alexander.held@fmf.uni-freiburg.de
License: wxWindows
Platform: UNKNOWN
